{
  "commit": "c0eae05",
  "parent": "93086bd79238114af54dbcbf6c498f3bf7b8c85e",
  "repo": "D:\\locbench\\pyjwt",
  "num_files_in_diff": 7,
  "num_py_files_in_diff": 5,
  "num_seeds": 8,
  "seeds": [
    {
      "path": "jwt/api_jwk.py",
      "version": "new",
      "line": 5,
      "kind": "module",
      "qualname": "jwt.api_jwk",
      "span": null,
      "reason": "diff_new_line_outside_defs",
      "is_test": false,
      "seed_type": "code_change",
      "new_code": null,
      "old_code": null
    },
    {
      "path": "jwt/api_jwt.py",
      "version": "new",
      "line": 7,
      "kind": "module",
      "qualname": "jwt.api_jwt",
      "span": null,
      "reason": "diff_new_line_outside_defs",
      "is_test": false,
      "seed_type": "code_change",
      "new_code": null,
      "old_code": null
    },
    {
      "path": "jwt/help.py",
      "version": "new",
      "line": 15,
      "kind": "function",
      "qualname": "jwt.help.info",
      "span": [
        15,
        57
      ],
      "reason": "diff_new_line_in_def",
      "is_test": false,
      "seed_type": "code_change",
      "new_code": "def info() -> dict[str, dict[str, str]]:\n    \"\"\"\n    Generate information for a bug report.\n    Based on the requests package help utility module.\n    \"\"\"\n    try:\n        platform_info = {\n            \"system\": platform.system(),\n            \"release\": platform.release(),\n        }\n    except OSError:\n        platform_info = {\"system\": \"Unknown\", \"release\": \"Unknown\"}\n\n    implementation = platform.python_implementation()\n\n    if implementation == \"CPython\":\n        implementation_version = platform.python_version()\n    elif implementation == \"PyPy\":\n        pypy_version_info = sys.pypy_version_info  # type: ignore[attr-defined]\n        implementation_version = (\n            f\"{pypy_version_info.major}.\"\n            f\"{pypy_version_info.minor}.\"\n            f\"{pypy_version_info.micro}\"\n        )\n        if pypy_version_info.releaselevel != \"final\":\n            implementation_version = \"\".join(\n                [\n                    implementation_version,\n                    pypy_version_info.releaselevel,\n                ]\n            )\n    else:\n        implementation_version = \"Unknown\"\n\n    return {\n        \"platform\": platform_info,\n        \"implementation\": {\n            \"name\": implementation,\n            \"version\": implementation_version,\n        },\n        \"cryptography\": {\"version\": cryptography_version},\n        \"pyjwt\": {\"version\": pyjwt_version},\n    }",
      "old_code": "def info() -> Dict[str, Dict[str, str]]:\n    \"\"\"\n    Generate information for a bug report.\n    Based on the requests package help utility module.\n    \"\"\"\n    try:\n        platform_info = {\n            \"system\": platform.system(),\n            \"release\": platform.release(),\n        }\n    except OSError:\n        platform_info = {\"system\": \"Unknown\", \"release\": \"Unknown\"}\n\n    implementation = platform.python_implementation()\n\n    if implementation == \"CPython\":\n        implementation_version = platform.python_version()\n    elif implementation == \"PyPy\":\n        pypy_version_info = sys.pypy_version_info  # type: ignore[attr-defined]\n        implementation_version = (\n            f\"{pypy_version_info.major}.\"\n            f\"{pypy_version_info.minor}.\"\n            f\"{pypy_version_info.micro}\"\n        )\n        if pypy_version_info.releaselevel != \"final\":\n            implementation_version = \"\".join(\n                [\n                    implementation_version,\n                    pypy_version_info.releaselevel,\n                ]\n            )\n    else:\n        implementation_version = \"Unknown\"\n\n    return {\n        \"platform\": platform_info,\n        \"implementation\": {\n            \"name\": implementation,\n            \"version\": implementation_version,\n        },\n        \"cryptography\": {\"version\": cryptography_version},\n        \"pyjwt\": {\"version\": pyjwt_version},\n    }"
    },
    {
      "path": "jwt/jwks_client.py",
      "version": "new",
      "line": 7,
      "kind": "module",
      "qualname": "jwt.jwks_client",
      "span": null,
      "reason": "diff_new_line_outside_defs",
      "is_test": false,
      "seed_type": "code_change",
      "new_code": null,
      "old_code": null
    },
    {
      "path": "jwt/jwks_client.py",
      "version": "new",
      "line": 24,
      "kind": "function",
      "qualname": "jwt.jwks_client.PyJWKClient.__init__",
      "span": [
        17,
        52
      ],
      "reason": "diff_new_line_in_def",
      "is_test": false,
      "seed_type": "code_change",
      "new_code": "    def __init__(\n        self,\n        uri: str,\n        cache_keys: bool = False,\n        max_cached_keys: int = 16,\n        cache_jwk_set: bool = True,\n        lifespan: float = 300,\n        headers: dict[str, Any] | None = None,\n        timeout: float = 30,\n        ssl_context: SSLContext | None = None,\n    ):\n        if headers is None:\n            headers = {}\n        self.uri = uri\n        self.jwk_set_cache: JWKSetCache | None = None\n        self.headers = headers\n        self.timeout = timeout\n        self.ssl_context = ssl_context\n\n        if cache_jwk_set:\n            # Init jwt set cache with default or given lifespan.\n            # Default lifespan is 300 seconds (5 minutes).\n            if lifespan <= 0:\n                raise PyJWKClientError(\n                    f'Lifespan must be greater than 0, the input is \"{lifespan}\"'\n                )\n            self.jwk_set_cache = JWKSetCache(lifespan)\n        else:\n            self.jwk_set_cache = None\n\n        if cache_keys:\n            # Cache signing keys\n            # Ignore mypy (https://github.com/python/mypy/issues/2427)\n            self.get_signing_key = lru_cache(maxsize=max_cached_keys)(\n                self.get_signing_key\n            )  # type: ignore",
      "old_code": "    def __init__(\n        self,\n        uri: str,\n        cache_keys: bool = False,\n        max_cached_keys: int = 16,\n        cache_jwk_set: bool = True,\n        lifespan: float = 300,\n        headers: Optional[Dict[str, Any]] = None,\n        timeout: float = 30,\n        ssl_context: Optional[SSLContext] = None,\n    ):\n        if headers is None:\n            headers = {}\n        self.uri = uri\n        self.jwk_set_cache: Optional[JWKSetCache] = None\n        self.headers = headers\n        self.timeout = timeout\n        self.ssl_context = ssl_context\n\n        if cache_jwk_set:\n            # Init jwt set cache with default or given lifespan.\n            # Default lifespan is 300 seconds (5 minutes).\n            if lifespan <= 0:\n                raise PyJWKClientError(\n                    f'Lifespan must be greater than 0, the input is \"{lifespan}\"'\n                )\n            self.jwk_set_cache = JWKSetCache(lifespan)\n        else:\n            self.jwk_set_cache = None\n\n        if cache_keys:\n            # Cache signing keys\n            # Ignore mypy (https://github.com/python/mypy/issues/2427)\n            self.get_signing_key = lru_cache(maxsize=max_cached_keys)(\n                self.get_signing_key\n            )  # type: ignore"
    },
    {
      "path": "jwt/jwks_client.py",
      "version": "new",
      "line": 85,
      "kind": "function",
      "qualname": "jwt.jwks_client.PyJWKClient.get_signing_keys",
      "span": [
        85,
        96
      ],
      "reason": "diff_new_line_in_def",
      "is_test": false,
      "seed_type": "code_change",
      "new_code": "    def get_signing_keys(self, refresh: bool = False) -> list[PyJWK]:\n        jwk_set = self.get_jwk_set(refresh)\n        signing_keys = [\n            jwk_set_key\n            for jwk_set_key in jwk_set.keys\n            if jwk_set_key.public_key_use in [\"sig\", None] and jwk_set_key.key_id\n        ]\n\n        if not signing_keys:\n            raise PyJWKClientError(\"The JWKS endpoint did not contain any signing keys\")\n\n        return signing_keys",
      "old_code": "    def get_signing_keys(self, refresh: bool = False) -> List[PyJWK]:\n        jwk_set = self.get_jwk_set(refresh)\n        signing_keys = [\n            jwk_set_key\n            for jwk_set_key in jwk_set.keys\n            if jwk_set_key.public_key_use in [\"sig\", None] and jwk_set_key.key_id\n        ]\n\n        if not signing_keys:\n            raise PyJWKClientError(\"The JWKS endpoint did not contain any signing keys\")\n\n        return signing_keys"
    },
    {
      "path": "jwt/jwks_client.py",
      "version": "new",
      "line": 120,
      "kind": "function",
      "qualname": "jwt.jwks_client.PyJWKClient.match_kid",
      "span": [
        120,
        128
      ],
      "reason": "diff_new_line_in_def",
      "is_test": false,
      "seed_type": "code_change",
      "new_code": "    def match_kid(signing_keys: list[PyJWK], kid: str) -> PyJWK | None:\n        signing_key = None\n\n        for key in signing_keys:\n            if key.key_id == kid:\n                signing_key = key\n                break\n\n        return signing_key",
      "old_code": "    def match_kid(signing_keys: List[PyJWK], kid: str) -> Optional[PyJWK]:\n        signing_key = None\n\n        for key in signing_keys:\n            if key.key_id == kid:\n                signing_key = key\n                break\n\n        return signing_key"
    },
    {
      "path": "jwt/types.py",
      "version": "new",
      "line": 1,
      "kind": "module",
      "qualname": "jwt.types",
      "span": null,
      "reason": "diff_new_line_outside_defs",
      "is_test": false,
      "seed_type": "code_change",
      "new_code": null,
      "old_code": null
    }
  ],
  "generated_at": "2026-02-10T15:15:22"
}